parampacmap/__init__.py
parampacmap/parampacmap.py
parampacmap/training.py
parampacmap/models/__init__.py
parampacmap/models/dataset.py
parampacmap/models/module.py
parampacmap/utils/__init__.py
parampacmap/utils/data.py
parampacmap/utils/utils.py
parampacmap-0.1.0.dist-info/METADATA
parampacmap-0.1.0.dist-info/WHEEL
parampacmap-0.1.0.dist-info/licenses/LICENSE
parampacmap-0.1.0.dist-info/RECORD
