Metadata-Version: 2.3
Name: parampacmap
Version: 0.1.0
Summary: Package for Parameterized PaCMAP (ParamRepulsor).
Author-email: Haiyang Huang <hyhuang@cs.duke.edu>, Michael Pilosov <consistentbayes@gmail.com>
Classifier: Intended Audience :: Developers
Classifier: Intended Audience :: Science/Research
Classifier: License :: OSI Approved :: Apache Software License
Classifier: Operating System :: OS Independent
Classifier: Programming Language :: Python :: 3
Requires-Python: <3.12,>=3.9
Requires-Dist: annoy>=1.17
Requires-Dist: numba==0.60.0
Requires-Dist: numpy<2.1,>=1.20
Requires-Dist: scikit-learn>=0.20
Provides-Extra: cpu
Requires-Dist: torch>=2.1.0; extra == 'cpu'
Provides-Extra: cu118
Requires-Dist: torch>=2.1.0; extra == 'cu118'
Provides-Extra: cu121
Requires-Dist: torch>=2.3.0; extra == 'cu121'
Provides-Extra: cu124
Requires-Dist: torch>=2.5.1; extra == 'cu124'
Provides-Extra: extras
Requires-Dist: pyyaml>=6.0.2; extra == 'extras'
Provides-Extra: mps
Requires-Dist: torch>=2.5.1; extra == 'mps'
Provides-Extra: torch200
Requires-Dist: torch==2.0.0; extra == 'torch200'
